libdescriptor/__init__.py
libdescriptor/libdescriptor.cpython-310-darwin.so
libdescriptor/libdescriptor.cpython-311-darwin.so
libdescriptor/libdescriptor.cpython-38-darwin.so
libdescriptor/libdescriptor.cpython-39-darwin.so
libdescriptor/libdescriptor.dylib
libdescriptor/libdescriptor.pyi
libdescriptor/neighbor.py
libdescriptor-0.2.3.dist-info/METADATA
libdescriptor-0.2.3.dist-info/WHEEL
libdescriptor-0.2.3.dist-info/top_level.txt
libdescriptor-0.2.3.dist-info/RECORD
