Metadata-Version: 2.1
Name: libdescriptor
Version: 0.2.3
Summary: Fully differentiable descriptors for atomistic systems
Author: Amit Gupta
Author-email: gupta839@umn.edu
Project-URL: Documentation, https://libdescriptor.readthedocs.io/
Requires-Dist: numpy
Requires-Dist: ase
Requires-Dist: pybind11
